pytest_voluptuous/__init__.py
pytest_voluptuous/plugin.py
pytest_voluptuous/validators.py
pytest_voluptuous/voluptuous.py
pytest_voluptuous-1.2.0.dist-info/LICENSE.rst
pytest_voluptuous-1.2.0.dist-info/METADATA
pytest_voluptuous-1.2.0.dist-info/WHEEL
pytest_voluptuous-1.2.0.dist-info/entry_points.txt
pytest_voluptuous-1.2.0.dist-info/top_level.txt
pytest_voluptuous-1.2.0.dist-info/RECORD
