Metadata-Version: 2.1
Name: pytest-voluptuous
Version: 1.2.0
Summary: Pytest plugin for asserting data against voluptuous schema.
Home-page: https://github.com/f-secure/pytest-voluptuous
Author: F-Secure Corporation
Author-email: opensource@f-secure.com
License: ASL 2.0
Platform: UNKNOWN
Classifier: Intended Audience :: Developers
Classifier: Framework :: Pytest
Classifier: License :: OSI Approved :: Apache Software License
Classifier: Operating System :: OS Independent
Classifier: Topic :: Software Development :: Testing
Classifier: Topic :: Software Development :: Libraries
Classifier: Programming Language :: Python :: 2.7
Classifier: Programming Language :: Python :: 3.4
Classifier: Programming Language :: Python :: 3.5
Classifier: Programming Language :: Python :: 3.6
Classifier: Programming Language :: Python :: 3.7
Classifier: Programming Language :: Python :: 3.8
Requires-Python: >=2.7, !=3.0.*, !=3.1.*, !=3.2.*, !=3.3.*
Requires-Dist: pytest
Requires-Dist: voluptuous (>=0.9.0)
